shandryll_reader/__init__.py
shandryll_reader/__main__.py
shandryll_reader/entities.py
shandryll_reader/feed.py
shandryll_reader/ui.py
shandryll_reader-0.1.0.dist-info/LICENSE
shandryll_reader-0.1.0.dist-info/METADATA
shandryll_reader-0.1.0.dist-info/WHEEL
shandryll_reader-0.1.0.dist-info/entry_points.txt
shandryll_reader-0.1.0.dist-info/top_level.txt
shandryll_reader-0.1.0.dist-info/RECORD
