Metadata-Version: 2.1
Name: shandryll_reader
Version: 0.1.0
Summary: Um simples leitor de artigos do blog da TreinaWeb
Author-email: Shandryll Stéphano <fo114381@inter.co>
License: MIT License
Keywords: twblog,treinaweb,blog,terminal,cli
Classifier: Environment :: Console
Classifier: License :: OSI Approved :: MIT License
Classifier: Natural Language :: Portuguese (Brazilian)
Classifier: Operating System :: OS Independent
Classifier: Programming Language :: Python :: 3
Classifier: Programming Language :: Python :: 3.9
Classifier: Programming Language :: Python :: 3.10
Classifier: Topic :: Utilities
Requires-Python: >=3.9
License-File: LICENSE
Requires-Dist: requests >=2.28.1
Requires-Dist: html2text >=2020.1.16
Requires-Dist: beautifulsoup4 >=4.11.1
Provides-Extra: build
Requires-Dist: build ; extra == 'build'
Requires-Dist: twine ; extra == 'build'
Provides-Extra: dev
Requires-Dist: black ; extra == 'dev'
Requires-Dist: mypy ; extra == 'dev'
Requires-Dist: types-requests >=2.28.9 ; extra == 'dev'
